pyfwht/__init__.py
pyfwht/_pyfwht.cpython-313-darwin.so
pyfwht/_version.py
pyfwht-1.1.4.dist-info/licenses/LICENSE
pyfwht-1.1.4.dist-info/METADATA
pyfwht-1.1.4.dist-info/WHEEL
pyfwht-1.1.4.dist-info/top_level.txt
pyfwht-1.1.4.dist-info/RECORD
