Metadata-Version: 2.4
Name: pyfwht
Version: 1.1.4
Summary: Fast Walsh-Hadamard Transform with CPU, OpenMP, and CUDA backends
Author-email: Hosein Hadipour <hsn.hadipour@gmail.com>
License-Expression: GPL-3.0-or-later
Project-URL: Homepage, https://github.com/hadipourh/fwht
Project-URL: Repository, https://github.com/hadipourh/fwht
Project-URL: Documentation, https://github.com/hadipourh/fwht/blob/main/python/README.md
Project-URL: Issues, https://github.com/hadipourh/fwht/issues
Keywords: walsh-hadamard,fwht,cryptanalysis,boolean-functions,cuda,gpu,simd,vectorization
Classifier: Development Status :: 4 - Beta
Classifier: Intended Audience :: Science/Research
Classifier: Intended Audience :: Developers
Classifier: Programming Language :: Python :: 3
Classifier: Programming Language :: Python :: 3.8
Classifier: Programming Language :: Python :: 3.9
Classifier: Programming Language :: Python :: 3.10
Classifier: Programming Language :: Python :: 3.11
Classifier: Programming Language :: Python :: 3.12
Classifier: Programming Language :: C
Classifier: Programming Language :: C++
Classifier: Topic :: Scientific/Engineering :: Mathematics
Classifier: Topic :: Security :: Cryptography
Classifier: Operating System :: OS Independent
Requires-Python: >=3.8
License-File: LICENSE
Requires-Dist: numpy>=1.20.0
Provides-Extra: dev
Requires-Dist: pytest>=7.0; extra == "dev"
Requires-Dist: pytest-benchmark>=4.0; extra == "dev"
Requires-Dist: black>=23.0; extra == "dev"
Requires-Dist: mypy>=1.0; extra == "dev"
Requires-Dist: ruff>=0.1.0; extra == "dev"
Dynamic: license-file
